TimeTaggerRPC/__init__.py
TimeTaggerRPC/client.py
TimeTaggerRPC/helper.py
TimeTaggerRPC/server.py
timetaggerrpc-0.0.6.post1.dist-info/entry_points.txt
timetaggerrpc-0.0.6.post1.dist-info/LICENSE.txt
timetaggerrpc-0.0.6.post1.dist-info/WHEEL
timetaggerrpc-0.0.6.post1.dist-info/METADATA
timetaggerrpc-0.0.6.post1.dist-info/RECORD
