Metadata-Version: 2.1
Name: TimeTaggerRPC
Version: 0.0.6.post1
Summary: RPC for Swabian Instruments' Time Tagger
Home-page: https://github.com/swabianinstruments/TimeTaggerRPC
License: BSD 3-Clause
Author: Igor Shavrin, Swabian Instruments GmbH
Author-email: igor@swabianinstruments.com
Requires-Python: >=3.6,<4
Classifier: License :: OSI Approved :: BSD License
Classifier: Development Status :: 3 - Alpha
Classifier: Programming Language :: Python :: 3
Classifier: Programming Language :: Python :: 3.6
Classifier: Programming Language :: Python :: 3.7
Classifier: Programming Language :: Python :: 3.8
Classifier: Programming Language :: Python :: 3.9
Classifier: Programming Language :: Python :: 3.10
Classifier: Programming Language :: Python :: 3.11
Classifier: Programming Language :: Python :: 3.12
Classifier: Topic :: Software Development :: Libraries :: Python Modules
Classifier: Topic :: Scientific/Engineering
Classifier: Intended Audience :: Developers
Classifier: Intended Audience :: Science/Research
Requires-Dist: Pyro5
Requires-Dist: numpy
Project-URL: Documentation, https://timetaggerrpc.readthedocs.io/
Project-URL: Hardware, https://www.swabianinstruments.com/time-tagger/
